mnx/__init__.py
mnx/main.py
mnx/approx_linear_methods/AproxSolver.py
mnx/approx_linear_methods/GaussSeidel.py
mnx/approx_linear_methods/IMethod.py
mnx/approx_linear_methods/Jacobi.py
mnx/approx_linear_methods/Richardson.py
mnx/approx_linear_methods/__init__.py
mnx/core/__init__.py
mnx/core/matrix.py
mnx/diff/__init__.py
mnx/exact_linear_methods/Cholesky.py
mnx/exact_linear_methods/Gauss.py
mnx/exact_linear_methods/Gauss_Jordan.py
mnx/exact_linear_methods/IMethod.py
mnx/exact_linear_methods/LU.py
mnx/exact_linear_methods/Solver.py
mnx/exact_linear_methods/__init__.py
mnx/int/__init__.py
mnx/les/ApproximationSolver.py
mnx/les/ExactSolver.py
mnx/les/LinearSolver.py
mnx/les/__init__.py
mnx/les/solver_factory.py
mnx/linprog/__init__.py
mnx/polynomial/__init__.py
mnx/sel/Cholesky.py
mnx/sel/Gauss.py
mnx/sel/Gauss_Jordan.py
mnx/sel/IMethod.py
mnx/sel/LU.py
mnx/sel/Solver.py
mnx/sel/__init__.py
mnx/senl/__init__.py
mnx/utils/__init__.py
mnx/utils/linalg.py
mnx/utils/norms.py
mnx/utils/rule_out.py
mnx_solver-0.1.0.3.dist-info/LICENSE
mnx_solver-0.1.0.3.dist-info/METADATA
mnx_solver-0.1.0.3.dist-info/WHEEL
mnx_solver-0.1.0.3.dist-info/top_level.txt
mnx_solver-0.1.0.3.dist-info/RECORD
